zqb/__init__.py
zqb/cli.py
zqb/cli_config.py
zqb/utils.py
zqb-0.1.1.dist-info/WHEEL
zqb-0.1.1.dist-info/entry_points.txt
zqb-0.1.1.dist-info/METADATA
zqb-0.1.1.dist-info/RECORD
