Metadata-Version: 2.3
Name: zqb
Version: 0.1.1
Summary: Zackary's Quick Bench - simple cli tool to quickly run scripts
Author: ZackaryW
Author-email: ZackaryW <36378555+ZackaryW@users.noreply.github.com>
Requires-Dist: click>=8.3.0
Requires-Dist: click-shell>=2.1
Requires-Dist: keyring>=25.6.0
Requires-Python: >=3.10
